Cyc2018CsXuexiBiji20181106/README.md
Cyc2018CsXuexiBiji20181106/__init__.py
Cyc2018CsXuexiBiji20181106/__main__.py
Cyc2018CsXuexiBiji20181106/file.epub
Cyc2018CsXuexiBiji20181106/index.html
Cyc2018CsXuexiBiji20181106/css/__init__.py
Cyc2018CsXuexiBiji20181106/css/annotations.css
Cyc2018CsXuexiBiji20181106/css/main.css
Cyc2018CsXuexiBiji20181106/css/normalize.css
Cyc2018CsXuexiBiji20181106/css/popup.css
Cyc2018CsXuexiBiji20181106/font/__init__.py
Cyc2018CsXuexiBiji20181106/font/fontello.eot
Cyc2018CsXuexiBiji20181106/font/fontello.svg
Cyc2018CsXuexiBiji20181106/font/fontello.ttf
Cyc2018CsXuexiBiji20181106/font/fontello.woff
Cyc2018CsXuexiBiji20181106/img/__init__.py
Cyc2018CsXuexiBiji20181106/img/annotator-glyph-sprite.png
Cyc2018CsXuexiBiji20181106/img/annotator-icon-sprite.png
Cyc2018CsXuexiBiji20181106/img/apple-touch-icon.png
Cyc2018CsXuexiBiji20181106/img/cancelfullscreen.png
Cyc2018CsXuexiBiji20181106/img/close.png
Cyc2018CsXuexiBiji20181106/img/fullscreen.png
Cyc2018CsXuexiBiji20181106/img/loader.gif
Cyc2018CsXuexiBiji20181106/img/menu-icon.png
Cyc2018CsXuexiBiji20181106/img/save.png
Cyc2018CsXuexiBiji20181106/img/saved.png
Cyc2018CsXuexiBiji20181106/img/settings-s.png
Cyc2018CsXuexiBiji20181106/img/settings.png
Cyc2018CsXuexiBiji20181106/img/star.png
Cyc2018CsXuexiBiji20181106/js/__init__.py
Cyc2018CsXuexiBiji20181106/js/epub.js
Cyc2018CsXuexiBiji20181106/js/epub.min.js
Cyc2018CsXuexiBiji20181106/js/epub.min.map
Cyc2018CsXuexiBiji20181106/js/hooks.min.js
Cyc2018CsXuexiBiji20181106/js/hooks.min.map
Cyc2018CsXuexiBiji20181106/js/reader.js
Cyc2018CsXuexiBiji20181106/js/reader.js.map
Cyc2018CsXuexiBiji20181106/js/reader.min.js
Cyc2018CsXuexiBiji20181106/js/reader.min.map
Cyc2018CsXuexiBiji20181106/js/hooks/__init__.py
Cyc2018CsXuexiBiji20181106/js/hooks/extensions/__init__.py
Cyc2018CsXuexiBiji20181106/js/hooks/extensions/highlight.js
Cyc2018CsXuexiBiji20181106/js/libs/__init__.py
Cyc2018CsXuexiBiji20181106/js/libs/jquery.min.js
cyc2018_cs_xuexi_biji_20181106-2024.3.3.0.dist-info/METADATA
cyc2018_cs_xuexi_biji_20181106-2024.3.3.0.dist-info/WHEEL
cyc2018_cs_xuexi_biji_20181106-2024.3.3.0.dist-info/entry_points.txt
cyc2018_cs_xuexi_biji_20181106-2024.3.3.0.dist-info/top_level.txt
cyc2018_cs_xuexi_biji_20181106-2024.3.3.0.dist-info/RECORD
